kachy/__init__.py
kachy_valkey-0.1.8.dist-info/licenses/LICENSE
kachy_valkey-0.1.8.dist-info/METADATA
kachy_valkey-0.1.8.dist-info/WHEEL
kachy_valkey-0.1.8.dist-info/top_level.txt
kachy_valkey-0.1.8.dist-info/RECORD
